[
{"id":1,"name":"!!!","twitter":"@chkchkchk"},
{"id":2,"name":"chk chk chk","twitter":"@chkchkchk"},
{"id":3,"name":"7 Notas 7 Colores","twitter":"@???"},
{"id":4,"name":"Abdulla Rashim","twitter":"@???"},
{"id":5,"name":"About Leaving","twitter":"@???"},
{"id":6,"name":"The Afghan Whigs","twitter":"@???"},
{"id":7,"name":"Against Me!","twitter":"@???"},
{"id":8,"name":"Agorazein","twitter":"@???"},
{"id":9,"name":"Aldrin y Collins","twitter":"@???"},
{"id":10,"name":"Alex Cameron","twitter":"@???"},
{"id":11,"name":"Alexandra Savior","twitter":"@???"},
{"id":12,"name":"Alexis Taylor","twitter":"@???"},
{"id":13,"name":"Alien Tango","twitter":"@???"},
{"id":14,"name":"All Indians No Chief","twitter":"@???"},
{"id":15,"name":"Âme live","twitter":"@???"},
{"id":16,"name":"Angel Olsen","twitter":"@???"},
{"id":17,"name":"Angela","twitter":"@???"},
{"id":18,"name":"Anímic","twitter":"@???"},
{"id":19,"name":"Annette Peacock","twitter":"@???"},
{"id":20,"name":"Aphex Twin","twitter":"@???"},
{"id":21,"name":"Arcade Fire","twitter":"@???"},
{"id":22,"name":"Aries","twitter":"@???"},
{"id":23,"name":"Aurora Halal","twitter":"@???"},
{"id":24,"name":"Autarkic live","twitter":"@???"},
{"id":25,"name":"Avalon Emerson","twitter":"@???"},
{"id":26,"name":"BADBADNOTGOOD","twitter":"@???"},
{"id":27,"name":"Barbott","twitter":"@???"},
{"id":28,"name":"Belako","twitter":"@???"},
{"id":29,"name":"Belushi","twitter":"@???"},
{"id":30,"name":"Ben UFO","twitter":"@???"},
{"id":31,"name":"Berri Txarrak","twitter":"@???"},
{"id":32,"name":"Bicep live","twitter":"@???"},
{"id":33,"name":"The Black Angels","twitter":"@???"},
{"id":34,"name":"Bolga","twitter":"@???"},
{"id":35,"name":"Bon Iver","twitter":"@???"},
{"id":36,"name":"Broken Social Scene","twitter":"@???"},
{"id":37,"name":"Cigarettes After Sex","twitter":"@???"},
{"id":38,"name":"CLUBZ","twitter":"@???"},
{"id":39,"name":"Cocaine Piss","twitter":"@???"},
{"id":40,"name":"Dj Coco","twitter":"@???"},
{"id":41,"name":"Conttra","twitter":"@???"},
{"id":42,"name":"Converge","twitter":"@???"},
{"id":43,"name":"The Crab Apples","twitter":"@???"},
{"id":44,"name":"Cymbals Eat Guitars","twitter":"@???"},
{"id":45,"name":"The Damned","twitter":"@???"},
{"id":46,"name":"Dave P.","twitter":"@???"},
{"id":47,"name":"Death Grips","twitter":"@???"},
{"id":48,"name":"Descendents","twitter":"@???"},
{"id":49,"name":"Dirty Porko & Crie930","twitter":"@???"},
{"id":50,"name":"Dirty Porko","twitter":"@???"},
{"id":51,"name":"Crie930","twitter":"@???"},
{"id":52,"name":"Discos Paradiso Crew","twitter":"@???"},
{"id":53,"name":"Dixon","twitter":"@???"},
{"id":54,"name":"Don't DJ","twitter":"@???"},
{"id":55,"name":"Donallop","twitter":"@???"},
{"id":56,"name":"Dj Dustin","twitter":"@???"},
{"id":57,"name":"El Petit de Cal Eril","twitter":"@???"},
{"id":58,"name":"ELMINI","twitter":"@???"},
{"id":59,"name":"Elza Soares","twitter":"@???"},
{"id":60,"name":"Evripidis And His Tragedies","twitter":"@???"},
{"id":61,"name":"Fairmont live","twitter":"@???"},
{"id":62,"name":"Fatima Yamaha","twitter":"@???"},
{"id":63,"name":"Ferenc","twitter":"@???"},
{"id":64,"name":"Flying Lotus","twitter":"@???"},
{"id":65,"name":"Formation","twitter":"@???"},
{"id":66,"name":"Frank Ocean","twitter":"@???"},
{"id":67,"name":"Front 242","twitter":"@???"},
{"id":68,"name":"Fufanu","twitter":"@???"},
{"id":69,"name":"Gas","twitter":"@???"},
{"id":70,"name":"Glass Animals","twitter":"@???"},
{"id":71,"name":"Gojira","twitter":"@???"},
{"id":72,"name":"Golden Bug","twitter":"@???"},
{"id":73,"name":"Gordi","twitter":"@???"},
{"id":74,"name":"Grace Jones","twitter":"@???"},
{"id":75,"name":"Grandaddy","twitter":"@???"},
{"id":76,"name":"The Growlers","twitter":"@???"},
{"id":77,"name":"Hamilton Leithauser","twitter":"@???"},
{"id":78,"name":"The Harlock","twitter":"@???"},
{"id":79,"name":"Henrik Schwarz","twitter":"@???"},
{"id":80,"name":"Her Little Donkey","twitter":"@???"},
{"id":81,"name":"Huerco S.","twitter":"@???"},
{"id":82,"name":"HVOB","twitter":"@???"},
{"id":83,"name":"Ian Pooley","twitter":"@???"},
{"id":84,"name":"InnerCut","twitter":"@???"},
{"id":85,"name":"Iosonouncane","twitter":"@???"},
{"id":86,"name":"It's Not Not","twitter":"@???"},
{"id":87,"name":"Jackmaster","twitter":"@???"},
{"id":88,"name":"Japandroids","twitter":"@???"},
{"id":89,"name":"Jardín de la Croix","twitter":"@???"},
{"id":90,"name":"Jazz","twitter":"@???"},
{"id":91,"name":"Jeremy Jay","twitter":"@???"},
{"id":92,"name":"JMII","twitter":"@???"},
{"id":93,"name":"Joey Purp","twitter":"@???"},
{"id":94,"name":"John Talabot","twitter":"@???"},
{"id":95,"name":"Joy Orbison","twitter":"@???"},
{"id":96,"name":"Julia Jacklin","twitter":"@???"},
{"id":97,"name":"Julie Doiron","twitter":"@???"},
{"id":98,"name":"Junun","twitter":"@???"},
{"id":99,"name":"Kate Tempest","twitter":"@???"},
{"id":100,"name":"Keems","twitter":"@???"},
{"id":101,"name":"Kelly Lee Owens","twitter":"@???"},
{"id":102,"name":"Kepa Junkera & Los Hermanos Cubero","twitter":"@???"},
{"id":103,"name":"Kepa Junkera","twitter":"@???"},
{"id":104,"name":"Los Hermanos Cubero","twitter":"@???"},
{"id":105,"name":"Kevin Morby","twitter":"@???"},
{"id":106,"name":"Khidja live","twitter":"@???"},
{"id":107,"name":"Kiasmos dj set","twitter":"@???"},
{"id":108,"name":"King Gizzard & The Lizard Wizard","twitter":"@???"},
{"id":109,"name":"King Gizzard","twitter":"@???"},
{"id":110,"name":"The Lizard Wizard","twitter":"@???"},
{"id":111,"name":"King Krule","twitter":"@???"},
{"id":112,"name":"KiNK live","twitter":"@???"},
{"id":113,"name":"Kokoshca","twitter":"@???"},
{"id":114,"name":"Kornél Kovács","twitter":"@???"},
{"id":115,"name":"Lady Wray","twitter":"@???"},
{"id":116,"name":"Lauer","twitter":"@???"},
{"id":117,"name":"Les Cruet","twitter":"@???"},
{"id":118,"name":"Les Sueques","twitter":"@???"},
{"id":119,"name":"Let's Eat Grandma","twitter":"@???"},
{"id":120,"name":"Local Natives","twitter":"@???"},
{"id":121,"name":"Lord Of The Isles","twitter":"@???"},
{"id":122,"name":"Lvl Up","twitter":"@???"},
{"id":123,"name":"Mac DeMarco","twitter":"@???"},
{"id":124,"name":"The Magnetic Fields","twitter":"@???"},
{"id":125,"name":"The Make-Up","twitter":"@???"},
{"id":126,"name":"Mannequin Pussy","twitter":"@???"},
{"id":127,"name":"Màquina Total","twitter":"@???"},
{"id":128,"name":"Marc Piñol","twitter":"@???"},
{"id":129,"name":"Maresme","twitter":"@???"},
{"id":130,"name":"Marie Davidson","twitter":"@???"},
{"id":131,"name":"Marta Delmont","twitter":"@???"},
{"id":132,"name":"Marvin & Guy","twitter":"@???"},
{"id":133,"name":"Matrixxman","twitter":"@???"},
{"id":134,"name":"Medalla","twitter":"@???"},
{"id":135,"name":"Melange","twitter":"@???"},
{"id":136,"name":"Metronomy","twitter":"@???"},
{"id":137,"name":"Michael Mayer","twitter":"@???"},
{"id":138,"name":"Miguel","twitter":"@???"},
{"id":139,"name":"Mishima","twitter":"@???"},
{"id":140,"name":"Mitski","twitter":"@???"},
{"id":141,"name":"The  Molochs","twitter":"@???"},
{"id":142,"name":"Moscoman live band","twitter":"@???"},
{"id":143,"name":"Muñeco","twitter":"@???"},
{"id":144,"name":"Murdoc","twitter":"@???"},
{"id":145,"name":"Museless","twitter":"@???"},
{"id":146,"name":"The Mystery Lights","twitter":"@???"},
{"id":147,"name":"Neleonard","twitter":"@???"},
{"id":148,"name":"Nikki Lane","twitter":"@???"},
{"id":149,"name":"No Crafts","twitter":"@???"},
{"id":150,"name":"No Zu","twitter":"@???"},
{"id":151,"name":"Noga Erez","twitter":"@???"},
{"id":152,"name":"Nots","twitter":"@???"},
{"id":153,"name":"Ocellot","twitter":"@???"},
{"id":154,"name":"Odina","twitter":"@???"},
{"id":155,"name":"Operators","twitter":"@???"},
{"id":156,"name":"Papá Topo","twitter":"@???"},
{"id":157,"name":"Patrick Codenys (Front 242)","twitter":"@???"},
{"id":158,"name":"PAVVLA","twitter":"@???"},
{"id":159,"name":"Pearson Sound","twitter":"@???"},
{"id":160,"name":"Pedro Vian","twitter":"@???"},
{"id":161,"name":"Pender Street Steppers","twitter":"@???"},
{"id":162,"name":"Phurpa","twitter":"@???"},
{"id":163,"name":"Pinegrove","twitter":"@???"},
{"id":164,"name":"Playback Maracas","twitter":"@???"},
{"id":165,"name":"Polar Inertia","twitter":"@???"},
{"id":166,"name":"Polseguera","twitter":"@???"},
{"id":167,"name":"Pond","twitter":"@???"},
{"id":168,"name":"Preoccupations","twitter":"@???"},
{"id":169,"name":"Priests","twitter":"@???"},
{"id":170,"name":"Rebuig","twitter":"@???"},
{"id":171,"name":"Recondite live","twitter":"@???"},
{"id":172,"name":"Regalim","twitter":"@???"},
{"id":173,"name":"Retirada!","twitter":"@???"},
{"id":174,"name":"Romare live","twitter":"@???"},
{"id":175,"name":"Rosalía & Raül Refree","twitter":"@???"},
{"id":176,"name":"Rosalía","twitter":"@???"},
{"id":177,"name":"Raül Refree","twitter":"@???"},
{"id":178,"name":"Royal Trux","twitter":"@???"},
{"id":179,"name":"Run The Jewels","twitter":"@???"},
{"id":180,"name":"Ryder The Eagle","twitter":"@???"},
{"id":181,"name":"S U R V I V E","twitter":"@???"},
{"id":182,"name":"Saint Etienne","twitter":"@???"},
{"id":183,"name":"SALFVMAN","twitter":"@???"},
{"id":184,"name":"Sampha","twitter":"@???"},
{"id":185,"name":"Sau Poler","twitter":"@???"},
{"id":186,"name":"Seu Jorge","twitter":"@???"},
{"id":187,"name":"Shelby Grey","twitter":"@???"},
{"id":188,"name":"Shellac","twitter":"@???"},
{"id":189,"name":"Silent James","twitter":"@???"},
{"id":190,"name":"Sinkane","twitter":"@???"},
{"id":191,"name":"Skepta","twitter":"@???"},
{"id":192,"name":"Skinny Puppy","twitter":"@???"},
{"id":193,"name":"Slayer","twitter":"@???"},
{"id":194,"name":"Sleaford Mods","twitter":"@???"},
{"id":195,"name":"Sleep","twitter":"@???"},
{"id":196,"name":"Slim Cessna's Auto Club","twitter":"@???"},
{"id":197,"name":"Solange","twitter":"@???"},
{"id":198,"name":"Soledad Vélez","twitter":"@???"},
{"id":199,"name":"Sorry Kate","twitter":"@???"},
{"id":200,"name":"Swans","twitter":"@???"},
{"id":201,"name":"Swet Shop Boys","twitter":"@???"},
{"id":202,"name":"Talaboman","twitter":"@???"},
{"id":203,"name":"Teenage Fanclub","twitter":"@???"},
{"id":204,"name":"Dj Tennis","twitter":"@???"},
{"id":205,"name":"This Is Not This Heat","twitter":"@???"},
{"id":206,"name":"Triángulo de Amor Bizarro","twitter":"@???"},
{"id":207,"name":"Tuff City Kids","twitter":"@???"},
{"id":208,"name":"Tycho","twitter":"@???"},
{"id":209,"name":"Vaadat Charigim","twitter":"@???"},
{"id":210,"name":"vàlius + Carlora Serrahima","twitter":"@???"},
{"id":211,"name":"vàlius","twitter":"@???"},
{"id":212,"name":"Carlota Serrahima","twitter":"@???"},
{"id":213,"name":"Van Morrison","twitter":"@???"},
{"id":214,"name":"Vladimir Ivkovic","twitter":"@???"},
{"id":215,"name":"Vox Low","twitter":"@???"},
{"id":216,"name":"Wand","twitter":"@???"},
{"id":217,"name":"The Waterparties","twitter":"@???"},
{"id":218,"name":"The Wave Pictures","twitter":"@???"},
{"id":219,"name":"The Wedding Present","twitter":"@???"},
{"id":220,"name":"Weval","twitter":"@???"},
{"id":221,"name":"Weyes Blood","twitter":"@???"},
{"id":222,"name":"The Wheels","twitter":"@???"},
{"id":223,"name":"Whitney","twitter":"@???"},
{"id":224,"name":"Wild Beasts","twitter":"@???"},
{"id":225,"name":"William Tyler","twitter":"@???"},
{"id":226,"name":"The xx","twitter":"@???"},
{"id":227,"name":"Youandewan","twitter":"@???"},
{"id":228,"name":"Young Marco","twitter":"@???"},
{"id":229,"name":"The Zombies","twitter":"@???"},
{"id":230,"name":"Adelaida","twitter":"@???"},
{"id":231,"name":"Aeromoças e Tenistas Russas","twitter":"@???"},
{"id":232,"name":"Astronaut Project","twitter":"@???"},
{"id":233,"name":"BIKE","twitter":"@???"},
{"id":234,"name":"Billy Carter","twitter":"@???"},
{"id":235,"name":"De Mónaco","twitter":"@???"},
{"id":236,"name":"DIEALRIGHT","twitter":"@???"},
{"id":237,"name":"Entropia","twitter":"@???"},
{"id":238,"name":"Escorpio","twitter":"@???"},
{"id":239,"name":"FingerFingerrr","twitter":"@???"},
{"id":240,"name":"G-C","twitter":"@???"},
{"id":241,"name":"Gold Class","twitter":"@???"},
{"id":242,"name":"Hanba!","twitter":"@???"},
{"id":243,"name":"Inzul","twitter":"@???"},
{"id":244,"name":"JAAA!","twitter":"@???"},
{"id":245,"name":"Joel Sarakula","twitter":"@???"},
{"id":246,"name":"Leyya","twitter":"@???"},
{"id":247,"name":"Lígula","twitter":"@???"},
{"id":248,"name":"Liniker e os Caramelows","twitter":"@???"},
{"id":249,"name":"Marley BloO","twitter":"@???"},
{"id":250,"name":"Marrakesh","twitter":"@???"},
{"id":251,"name":"Me & The Plant","twitter":"@???"},
{"id":252,"name":"Meridian Response","twitter":"@???"},
{"id":253,"name":"Miss Garrison","twitter":"@???"},
{"id":254,"name":"no metal in this battle","twitter":"@???"},
{"id":255,"name":"PATiENTS","twitter":"@???"},
{"id":256,"name":"Persian Pelican","twitter":"@???"},
{"id":257,"name":"Prairie WWWW","twitter":"@???"},
{"id":258,"name":"Radio 123","twitter":"@???"},
{"id":259,"name":"RBP","twitter":"@???"},
{"id":260,"name":"Riviere","twitter":"@???"},
{"id":261,"name":"SHAO","twitter":"@???"},
{"id":262,"name":"Sharman Den","twitter":"@???"},
{"id":263,"name":"Shijo X","twitter":"@???"},
{"id":264,"name":"Skegss","twitter":"@???"},
{"id":265,"name":"Tiê","twitter":"@???"},
{"id":266,"name":"Tired Lion","twitter":"@???"},
{"id":267,"name":"Tourista","twitter":"@???"},
{"id":268,"name":"Wrongonyou","twitter":"@???"}
]